README.rst
setup.cfg
setup.py
./__init__.py
./dummy.py
./manual.py
./transaction.py
./transaction.xml
./tryton.cfg
./locale/de_DE.po
./tests/__init__.py
./tests/test_transaction.py
./tests/test_view_depends.py
./view/gateway_form.xml
./view/gateway_list.xml
./view/party_payment_profile_form.xml
./view/payment_profile_add_form.xml
./view/payment_profile_form.xml
./view/payment_profile_list.xml
./view/transaction_form.xml
./view/transaction_list.xml
./view/transaction_log_form.xml
./view/transaction_log_list.xml
./view/transaction_use_card_form.xml
./view/user_form.xml
openlabs_payment_gateway.egg-info/PKG-INFO
openlabs_payment_gateway.egg-info/SOURCES.txt
openlabs_payment_gateway.egg-info/dependency_links.txt
openlabs_payment_gateway.egg-info/entry_points.txt
openlabs_payment_gateway.egg-info/not-zip-safe
openlabs_payment_gateway.egg-info/requires.txt
openlabs_payment_gateway.egg-info/top_level.txt